app/.gitignore
app/__init__.py
app/app.py
app/config.py
app/views.py
app/api/__init__.py
app/api/code.py
app/api/models/__init__.py
app/api/models/code_schema.py
app/public/3rdpartylicenses.txt
app/public/browser/chunk-2YJAEF6H.js
app/public/browser/chunk-Q7OOHYGW.js
app/public/browser/favicon.ico
app/public/browser/index.html
app/public/browser/main-7K7NF7WX.js
app/public/browser/polyfills-A7MJM4D4.js
app/public/browser/styles-IK6WSUX4.css
app/public/browser/assets/monaco/CHANGELOG.md
app/public/browser/assets/monaco/LICENSE
app/public/browser/assets/monaco/README.md
app/public/browser/assets/monaco/ThirdPartyNotices.txt
app/public/browser/assets/monaco/monaco.d.ts
app/public/browser/assets/monaco/package.json
app/public/browser/assets/monaco/dev/bundleInfo.json
app/public/browser/assets/monaco/dev/nls.metadata.json
app/public/browser/assets/monaco/dev/vs/loader.js
app/public/browser/assets/monaco/dev/vs/base/browser/ui/codicons/codicon/codicon.ttf
app/public/browser/assets/monaco/dev/vs/base/common/worker/simpleWorker.nls.de.js
app/public/browser/assets/monaco/dev/vs/base/common/worker/simpleWorker.nls.es.js
app/public/browser/assets/monaco/dev/vs/base/common/worker/simpleWorker.nls.fr.js
app/public/browser/assets/monaco/dev/vs/base/common/worker/simpleWorker.nls.it.js
app/public/browser/assets/monaco/dev/vs/base/common/worker/simpleWorker.nls.ja.js
app/public/browser/assets/monaco/dev/vs/base/common/worker/simpleWorker.nls.js
app/public/browser/assets/monaco/dev/vs/base/common/worker/simpleWorker.nls.ko.js
app/public/browser/assets/monaco/dev/vs/base/common/worker/simpleWorker.nls.ru.js
app/public/browser/assets/monaco/dev/vs/base/common/worker/simpleWorker.nls.zh-cn.js
app/public/browser/assets/monaco/dev/vs/base/common/worker/simpleWorker.nls.zh-tw.js
app/public/browser/assets/monaco/dev/vs/base/worker/workerMain.js
app/public/browser/assets/monaco/dev/vs/base/worker/workerMain.js.map
app/public/browser/assets/monaco/dev/vs/basic-languages/abap/abap.js
codeguessr-0.0.2.dist-info/METADATA
codeguessr-0.0.2.dist-info/WHEEL
codeguessr-0.0.2.dist-info/entry_points.txt
codeguessr-0.0.2.dist-info/licenses/LICENSE.txt
codeguessr-0.0.2.dist-info/RECORD
