Metadata-Version: 2.3
Name: codeguessr
Version: 0.0.2
Summary: Simple game to help explore a code-base.
Author-email: Eric Roeum <eroeum@gmail.com>
License: # Released under MIT License
License-File: LICENSE.txt
Requires-Python: >3.8
Requires-Dist: flask
Requires-Dist: flask-bootstrap
Requires-Dist: flask-cors
Requires-Dist: flask-smorest
Requires-Dist: gitpython
Requires-Dist: hatchling
